easonc/__init__.py
easonc-0.1.dist-info/LICENSE
easonc-0.1.dist-info/METADATA
easonc-0.1.dist-info/WHEEL
easonc-0.1.dist-info/top_level.txt
easonc-0.1.dist-info/RECORD
