Metadata-Version: 2.1
Name: easonc
Version: 0.1
Summary: easonc test
Home-page: https://github.com/EasonC13/easonc
Author: EasonC13
Author-email: eason.tw.chen@gmail.com
License: MIT
Platform: UNKNOWN
Classifier: Programming Language :: Python :: 3
Classifier: License :: OSI Approved :: MIT License
Classifier: Operating System :: OS Independent
Requires-Python: >=3.6
